[
  {
    "item": "00 flour",
    "available": false,
    "aisle": null,
    "price": null,
    "product_url": null
  },
  {
    "item": "mozzarella cheese",
    "available": true,
    "aisle": "D1",
    "price": 3.99,
    "product_url": "https://www.target.com/p/mozzarella-cheese/-/A12345678"
  },
  {
    "item": "san marzano tomatoes",
    "available": false,
    "aisle": null,
    "price": null,
    "product_url": null
  },
  {
    "item": "fresh basil",
    "available": true,
    "aisle": "A4",
    "price": 1.45,
    "product_url": "https://www.target.com/p/fresh-basil/-/A12345678"
  },
  {
    "item": "olive oil",
    "available": true,
    "aisle": "A1",
    "price": 2.61,
    "product_url": "https://www.target.com/p/olive-oil/-/A12345678"
  }
]